llm_gemini_code_assist.py
llm_gemini_code_assist-0.28.2.dist-info/METADATA
llm_gemini_code_assist-0.28.2.dist-info/WHEEL
llm_gemini_code_assist-0.28.2.dist-info/entry_points.txt
llm_gemini_code_assist-0.28.2.dist-info/licenses/LICENSE
llm_gemini_code_assist-0.28.2.dist-info/RECORD
