Metadata-Version: 2.4
Name: llm-gemini-code-assist
Version: 0.28.2
Summary: LLM plugin to access Google's Gemini via Code Assist API with OAuth
Project-URL: Homepage, https://github.com/lokkju/llm-gemini-code-assist
Project-URL: Issues, https://github.com/lokkju/llm-gemini-code-assist/issues
Author: Loki Coyote, Simon Willison
License-Expression: Apache-2.0
License-File: LICENSE
Requires-Python: >=3.10
Requires-Dist: google-auth-oauthlib>=1.2.2
Requires-Dist: google-auth>=2.43.0
Requires-Dist: httpx>=0.28.1
Requires-Dist: ijson>=3.4.0.post0
Requires-Dist: llm>=0.28
Requires-Dist: pyjwt>=2.10.1
Requires-Dist: requests>=2.32.5
